maxent_disaggregation/__init__.py
maxent_disaggregation/maxent_direchlet.py
maxent_disaggregation/maxent_disaggregation.py
maxent_disaggregation/shares.py
maxent_disaggregation-1.0.10.dist-info/licenses/LICENSE
maxent_disaggregation-1.0.10.dist-info/METADATA
maxent_disaggregation-1.0.10.dist-info/WHEEL
maxent_disaggregation-1.0.10.dist-info/top_level.txt
maxent_disaggregation-1.0.10.dist-info/RECORD
