Metadata-Version: 2.4
Name: maxent_disaggregation
Version: 1.0.10
Summary: Package to help with the propagation of uncertainty when disaggregating data, using the maximum entropy principle.
Author-email: Arthur Jakobs <artos.jakobs@psi.ch>, Simon Schulte <simonsc@plan.aau.dk>
Maintainer-email: Arthur Jakobs <artos.jakobs@psi.ch>
License: MIT
Project-URL: source, https://github.com/jakobsarthur/maxent_disaggregation
Project-URL: homepage, https://github.com/jakobsarthur/maxent_disaggregation
Project-URL: tracker, https://github.com/jakobsarthur/maxent_disaggregation/issues
Classifier: Development Status :: 4 - Beta
Classifier: Programming Language :: Python
Classifier: Programming Language :: Python :: 3
Classifier: Programming Language :: Python :: 3.9
Classifier: Programming Language :: Python :: 3.10
Classifier: Programming Language :: Python :: 3.11
Classifier: Programming Language :: Python :: 3.12
Classifier: Programming Language :: Python :: 3.13
Classifier: Natural Language :: English
Classifier: Operating System :: OS Independent
Classifier: Topic :: Scientific/Engineering
Requires-Python: <3.14,>=3.9
License-File: LICENSE
Requires-Dist: scipy
Requires-Dist: numpy
Requires-Dist: nlopt
Provides-Extra: testing
Requires-Dist: maxent_disaggregation; extra == "testing"
Requires-Dist: pytest; extra == "testing"
Requires-Dist: pytest-cov; extra == "testing"
Requires-Dist: python-coveralls; extra == "testing"
Provides-Extra: dev
Requires-Dist: build; extra == "dev"
Requires-Dist: pre-commit; extra == "dev"
Requires-Dist: pylint; extra == "dev"
Requires-Dist: pytest; extra == "dev"
Requires-Dist: pytest-cov; extra == "dev"
Requires-Dist: pytest-randomly; extra == "dev"
Requires-Dist: setuptools; extra == "dev"
Provides-Extra: notebooks
Requires-Dist: jupyterlab; extra == "notebooks"
Requires-Dist: ipykernel; extra == "notebooks"
Requires-Dist: matplotlib; extra == "notebooks"
Requires-Dist: corner; extra == "notebooks"
Requires-Dist: numpy; extra == "notebooks"
Requires-Dist: scipy; extra == "notebooks"
Requires-Dist: pandas; extra == "notebooks"
Requires-Dist: seaborn; extra == "notebooks"
Requires-Dist: corner; extra == "notebooks"
Dynamic: license-file
